charity/__init__.py
charity/__main__.py
charity/charset.py
charity/main.py
charity/trie.py
charity-0.1.0.dist-info/METADATA
charity-0.1.0.dist-info/WHEEL
charity-0.1.0.dist-info/entry_points.txt
charity-0.1.0.dist-info/RECORD
