Metadata-Version: 2.4
Name: charity
Version: 0.1.0
Summary: Build and render a Trie from newline-separated input using Graphviz.
Project-URL: Homepage, https://github.com/yaccob/charity
Project-URL: Source, https://github.com/yaccob/charity
Requires-Python: >=3.9
Requires-Dist: graphviz>=0.21
Provides-Extra: dev
Requires-Dist: build; extra == 'dev'
Requires-Dist: twine; extra == 'dev'
